Products.DCWorkflow-3.0-py3.11-nspkg.pth
Products/DCWorkflow/ContainerTab.py
Products/DCWorkflow/DCWorkflow.py
Products/DCWorkflow/Expression.py
Products/DCWorkflow/Guard.py
Products/DCWorkflow/Scripts.py
Products/DCWorkflow/States.py
Products/DCWorkflow/Transitions.py
Products/DCWorkflow/Variables.py
Products/DCWorkflow/WorkflowUIMixin.py
Products/DCWorkflow/Worklists.py
Products/DCWorkflow/__init__.py
Products/DCWorkflow/configure.zcml
Products/DCWorkflow/events.py
Products/DCWorkflow/exportimport.py
Products/DCWorkflow/exportimport.zcml
Products/DCWorkflow/interfaces.py
Products/DCWorkflow/permissions.py
Products/DCWorkflow/testing.py
Products/DCWorkflow/tool.zcml
Products/DCWorkflow/utils.py
Products/DCWorkflow/Extensions/test_method.py
Products/DCWorkflow/browser/__init__.py
Products/DCWorkflow/browser/configure.zcml
Products/DCWorkflow/browser/workflow.py
Products/DCWorkflow/doc/examples/staging/checkin.py
Products/DCWorkflow/doc/examples/staging/checkout.py
Products/DCWorkflow/doc/examples/staging/retractStages.py
Products/DCWorkflow/doc/examples/staging/updateProductionStage.py
Products/DCWorkflow/doc/examples/staging/updateReviewStage.py
Products/DCWorkflow/dtml/guard.dtml
Products/DCWorkflow/dtml/state_groups.pt
Products/DCWorkflow/dtml/state_permissions.dtml
Products/DCWorkflow/dtml/state_properties.dtml
Products/DCWorkflow/dtml/state_variables.dtml
Products/DCWorkflow/dtml/states.dtml
Products/DCWorkflow/dtml/transition_properties.dtml
Products/DCWorkflow/dtml/transition_variables.dtml
Products/DCWorkflow/dtml/transitions.dtml
Products/DCWorkflow/dtml/variable_properties.dtml
Products/DCWorkflow/dtml/variables.dtml
Products/DCWorkflow/dtml/workflow_groups.pt
Products/DCWorkflow/dtml/workflow_permissions.dtml
Products/DCWorkflow/dtml/workflow_properties.dtml
Products/DCWorkflow/dtml/worklist_properties.dtml
Products/DCWorkflow/dtml/worklists.dtml
Products/DCWorkflow/images/script.gif
Products/DCWorkflow/images/state.gif
Products.DCWorkflow-3.0.dist-info/LICENSE.txt
Products.DCWorkflow-3.0.dist-info/METADATA
Products.DCWorkflow-3.0.dist-info/WHEEL
Products.DCWorkflow-3.0.dist-info/entry_points.txt
Products.DCWorkflow-3.0.dist-info/namespace_packages.txt
Products.DCWorkflow-3.0.dist-info/top_level.txt
Products.DCWorkflow-3.0.dist-info/RECORD
