Metadata-Version: 2.1
Name: Products.DCWorkflow
Version: 3.0
Summary: DCWorkflow product for the Zope Content Management Framework
Home-page: https://pypi.org/project/Products.DCWorkflow
Author: Zope Foundation and Contributors
Author-email: zope-dev@zope.dev
License: ZPL 2.1
Project-URL: Issue Tracker, https://github.com/zopefoundation/Products.DCWorkflow/issues
Project-URL: Sources, https://github.com/zopefoundation/Products.DCWorkflow
Keywords: web application server zope cmf
Classifier: Development Status :: 5 - Production/Stable
Classifier: Framework :: Plone
Classifier: Framework :: Zope :: 5
Classifier: Intended Audience :: Developers
Classifier: License :: OSI Approved :: Zope Public License
Classifier: Programming Language :: Python :: 3
Classifier: Programming Language :: Python :: 3.7
Classifier: Programming Language :: Python :: 3.8
Classifier: Programming Language :: Python :: 3.9
Classifier: Programming Language :: Python :: 3.10
Classifier: Programming Language :: Python :: 3.11
Classifier: Topic :: Software Development
Classifier: Topic :: Software Development :: Libraries :: Application Frameworks
Requires-Python: >=3.7
License-File: LICENSE.txt
Requires-Dist: setuptools
Requires-Dist: Zope (>=5.0)
Requires-Dist: Products.CMFCore (>=2.4.0)
Requires-Dist: Products.ExternalMethod
Requires-Dist: Products.GenericSetup (>=2.0b1)
Requires-Dist: Products.PythonScripts
Provides-Extra: docs
Requires-Dist: Sphinx ; extra == 'docs'
Requires-Dist: repoze.sphinx.autointerface ; extra == 'docs'
Requires-Dist: pkginfo ; extra == 'docs'
